sketch/__init__.py
sketch/base.py
sketch/nodes.py
python_sketch-0.2.0.dist-info/LICENSE
python_sketch-0.2.0.dist-info/METADATA
python_sketch-0.2.0.dist-info/WHEEL
python_sketch-0.2.0.dist-info/top_level.txt
python_sketch-0.2.0.dist-info/RECORD
